{
  "configs": [
    {
      "inputPreset": "GENERIC",
      "sampleRate": 48000,
      "channelCount": 1,
      "format": 16,
      "performanceMode": "LOW_LATENCY",
      "sharingMode": "SHARED",
      "outputPath": "/data/standard_recording.wav",
      "description": "标准录音 - 48kHz单声道"
    },
    {
      "inputPreset": "VOICE_COMMUNICATION",
      "sampleRate": 16000,
      "channelCount": 1,
      "format": 16,
      "performanceMode": "LOW_LATENCY",
      "sharingMode": "SHARED",
      "outputPath": "",
      "description": "语音通话 - 16kHz单声道"
    },
    {
      "inputPreset": "VOICE_RECOGNITION",
      "sampleRate": 16000,
      "channelCount": 1,
      "format": 16,
      "performanceMode": "LOW_LATENCY",
      "sharingMode": "SHARED",
      "outputPath": "/data/voice_recognition.wav",
      "description": "语音识别 - 16kHz单声道"
    },
    {
      "inputPreset": "CAMCORDER",
      "sampleRate": 44100,
      "channelCount": 2,
      "format": 16,
      "performanceMode": "POWER_SAVING",
      "sharingMode": "SHARED",
      "outputPath": "",
      "description": "摄像录音 - 44.1kHz立体声"
    },
    {
      "inputPreset": "VOICE_PERFORMANCE",
      "sampleRate": 48000,
      "channelCount": 1,
      "format": 16,
      "performanceMode": "LOW_LATENCY",
      "sharingMode": "EXCLUSIVE",
      "outputPath": "",
      "description": "高性能语音 - 48kHz独占模式"
    },
    {
      "inputPreset": "UNPROCESSED",
      "sampleRate": 48000,
      "channelCount": 2,
      "format": 16,
      "performanceMode": "LOW_LATENCY",
      "sharingMode": "EXCLUSIVE",
      "outputPath": "/data/recorded_48k_2ch_16bit.wav",
      "description": "原始录音 - 48kHz立体声无处理"
    },
    {
      "inputPreset": "GENERIC",
      "sampleRate": 44100,
      "channelCount": 2,
      "format": 16,
      "performanceMode": "POWER_SAVING",
      "sharingMode": "SHARED",
      "outputPath": "",
      "description": "音乐录音 - 44.1kHz立体声"
    },
    {
      "inputPreset": "GENERIC",
      "sampleRate": 96000,
      "channelCount": 2,
      "format": 32,
      "performanceMode": "LOW_LATENCY",
      "sharingMode": "EXCLUSIVE",
      "outputPath": "",
      "description": "高保真录音 - 96kHz立体声32位"
    }
  ]
}